{
    "Ar36": {
        "error": 1.4347486536092946,
        "error_type": "",
        "fit": "previous",
        "references": [
            {
                "exclude": false,
                "record_id": "bu-CC-N-3849"
            }
        ],
        "value": 331.2965793167273
    },
    "Ar37": {
        "error": 3.897821950013294e-07,
        "error_type": "",
        "fit": "previous",
        "references": [
            {
                "exclude": false,
                "record_id": "bu-CC-N-3849"
            }
        ],
        "value": 3.592029399285289e-06
    },
    "Ar38": {
        "error": 3.86682500654113e-07,
        "error_type": "",
        "fit": "previous",
        "references": [
            {
                "exclude": false,
                "record_id": "bu-CC-N-3849"
            }
        ],
        "value": 3.9563902209016924e-06
    },
    "Ar39": {
        "error": 4.3554837699432313e-07,
        "error_type": "",
        "fit": "previous",
        "references": [
            {
                "exclude": false,
                "record_id": "bu-CC-N-3849"
            }
        ],
        "value": 3.451348770038672e-06
    },
    "Ar40": {
        "error": 1.5871184934998425e-06,
        "error_type": "",
        "fit": "previous",
        "references": [
            {
                "exclude": false,
                "record_id": "bu-CC-N-3849"
            }
        ],
        "value": 0.000977785593627405
    }
}