{
    "Ar36": {
        "error": 1.7401188718812455,
        "error_type": "",
        "fit": "previous",
        "references": [
            {
                "exclude": false,
                "record_id": "bu-CC-N-3771"
            }
        ],
        "value": 355.49512841661397
    },
    "Ar37": {
        "error": 4.759706787152501e-07,
        "error_type": "",
        "fit": "previous",
        "references": [
            {
                "exclude": false,
                "record_id": "bu-CC-N-3771"
            }
        ],
        "value": 4.5494251807326745e-06
    },
    "Ar38": {
        "error": 5.516263746708927e-07,
        "error_type": "",
        "fit": "previous",
        "references": [
            {
                "exclude": false,
                "record_id": "bu-CC-N-3771"
            }
        ],
        "value": 1.5661858513294852e-06
    },
    "Ar39": {
        "error": 3.7284676333596563e-07,
        "error_type": "",
        "fit": "previous",
        "references": [
            {
                "exclude": false,
                "record_id": "bu-CC-N-3771"
            }
        ],
        "value": 4.439269831186091e-06
    },
    "Ar40": {
        "error": 8.184070565406493e-07,
        "error_type": "",
        "fit": "previous",
        "references": [
            {
                "exclude": false,
                "record_id": "bu-CC-N-3771"
            }
        ],
        "value": 0.00047623953131388784
    }
}